Metadata-Version: 2.1
Name: sympy-add
Version: 1.3
Summary: Addition for sympy
Home-page: https://github.com/DaSh-More/SympyAdd
Author: DaSh-More
Author-email: danila-763@yandex.ru
License: MIT
Platform: any
Classifier: Development Status :: 4 - Beta
Classifier: Programming Language :: Python :: 3
License-File: LICENSE
